collective.behaviors-1.2.1-py2.7-nspkg.pth
collective/behaviors/__init__.py
collective/behaviors/configure.zcml
collective/behaviors/general.py
collective/behaviors/general.zcml
collective/behaviors/interfaces.py
collective/behaviors/meta.zcml
collective/behaviors/setuphandlers.py
collective/behaviors/testing.py
collective/behaviors/upgrades.zcml
collective/behaviors/util.py
collective/behaviors/vocabs.py
collective/behaviors/browser/__init__.py
collective/behaviors/browser/base64.py
collective/behaviors/browser/configure.zcml
collective/behaviors/browser/controlpanel.py
collective/behaviors/browser/overrides/.gitkeep
collective/behaviors/browser/static/.gitkeep
collective/behaviors/events/__init__.py
collective/behaviors/events/behaviors.py
collective/behaviors/events/configure.zcml
collective/behaviors/locales/collective.behaviors.pot
collective/behaviors/locales/update.sh
collective/behaviors/organisation/__init__.py
collective/behaviors/organisation/behaviors.py
collective/behaviors/organisation/configure.zcml
collective/behaviors/organisation/indexers.py
collective/behaviors/profiles/default/controlpanel.xml
collective/behaviors/profiles/default/metadata.xml
collective/behaviors/profiles/default/registry.xml
collective/behaviors/profiles/events/metadata.xml
collective/behaviors/profiles/organisation/catalog.xml
collective/behaviors/profiles/organisation/metadata.xml
collective/behaviors/profiles/uninstall/browserlayer.xml
collective/behaviors/tests/__init__.py
collective/behaviors/tests/test_robot.py
collective/behaviors/tests/test_setup.py
collective/behaviors/tests/robot/test_example.robot
collective.behaviors-1.2.1.dist-info/METADATA
collective.behaviors-1.2.1.dist-info/WHEEL
collective.behaviors-1.2.1.dist-info/entry_points.txt
collective.behaviors-1.2.1.dist-info/namespace_packages.txt
collective.behaviors-1.2.1.dist-info/top_level.txt
collective.behaviors-1.2.1.dist-info/RECORD
